{
  "records": [
    {
      "id": "rec05jPxexwMjDRCN",
      "createdTime": "2023-03-29T11:26:34.000Z",
      "fields": {
        "serializer": "L0",
        "function_name": [
          "recZLnkHAyzHc6z2s"
        ]
      }
    },
    {
      "id": "rec12HIThIfyrLaVW",
      "createdTime": "2023-09-27T00:07:04.000Z",
      "fields": {
        "serializer": "R1C$F$T$T1V$T2V$T3V$T4V$",
        "function_name": [
          "recsiuexAMgymTeUe"
        ]
      }
    },
    {
      "id": "rec12YB5oGkfS42Sy",
      "createdTime": "2023-03-29T11:26:34.000Z",
      "fields": {
        "serializer": "P2F",
        "function_name": [
          "recxTTPcOzgT6bKw0"
        ]
      }
    },
    {
      "id": "rec2VgfrikTFmwnnj",
      "createdTime": "2023-03-29T11:26:34.000Z",
      "fields": {
        "serializer": "B2B$",
        "function_name": [
          "recfgkKeG5DyAFhNW"
        ]
      }
    },
    {
      "id": "rec58wXFjuhTftEHr",
      "createdTime": "2023-03-29T11:26:34.000Z",
      "fields": {
        "serializer": "L$X$Y$R$G$B$",
        "function_name": [
          "reczDHAEgUkJLkcAK"
        ]
      }
    },
    {
      "id": "rec6Cg51RYBcTQZwa",
      "createdTime": "2023-03-30T08:35:07.000Z",
      "fields": {
        "serializer": "H0P0",
        "function_name": [
          "recu4eNuJ1FjbQeAG"
        ]
      }
    },
    {
      "id": "rec6aijmMkwmIsibc",
      "createdTime": "2023-03-29T11:26:34.000Z",
      "fields": {
        "serializer": "O1C",
        "function_name": [
          "recS5hKLt6sPtFGvz"
        ]
      }
    },
    {
      "id": "rec8bU2g28rxQ7Jjr",
      "createdTime": "2023-03-29T11:25:28.000Z",
      "fields": {
        "serializer": "A0S$A$",
        "function_name": [
          "recINYmlfJXrw97dn"
        ]
      }
    },
    {
      "id": "rec8n2zIJ5uZVAzWr",
      "createdTime": "2023-03-29T11:26:34.000Z",
      "fields": {
        "serializer": "O1T$Z$S$D$",
        "function_name": [
          "recCIuYVbwYUXKRRT"
        ]
      }
    },
    {
      "id": "recANyP3OxcGcBmgJ",
      "createdTime": "2023-03-29T11:26:34.000Z",
      "fields": {
        "serializer": "T1R$S$",
        "function_name": [
          "recOX0vMaD2LwqhmU"
        ]
      }
    },
    {
      "id": "recAwY2QticpQBH7v",
      "createdTime": "2023-03-29T11:26:34.000Z",
      "fields": {
        "serializer": "T1D",
        "function_name": [
          "recBJc28r8rwqbFoS"
        ]
      }
    },
    {
      "id": "recETB6QcIHXksvcP",
      "createdTime": "2023-03-29T11:26:34.000Z",
      "fields": {
        "serializer": "P2L$V$S$E$R$",
        "function_name": [
          "recwXrVSbZpeLIJTB"
        ]
      }
    },
    {
      "id": "recEtC9LZPAttO7t5",
      "createdTime": "2023-11-01T01:53:26.000Z",
      "fields": {
        "serializer": "RFID0",
        "function_name": [
          "recIqWcFRS3exe6k6"
        ]
      }
    },
    {
      "id": "recGB3p21xNcJ3d4G",
      "createdTime": "2023-06-29T07:29:21.000Z",
      "fields": {
        "serializer": "A0U$A$B$C$D$E$F$G$H$I$J$K$L$M$N$O$P$Q$R$S$T$U",
        "function_name": [
          "recDvTczNRMtNYM2A"
        ]
      }
    },
    {
      "id": "recMxAk1INWevQa59",
      "createdTime": "2023-03-29T11:26:34.000Z",
      "fields": {
        "serializer": "S1S$P$",
        "function_name": [
          "recRRaEliiTG4hrNm"
        ]
      }
    },
    {
      "id": "recPg57x0ovJFgXyT",
      "createdTime": "2023-03-29T11:26:34.000Z",
      "fields": {
        "serializer": "L0",
        "function_name": [
          "recWaLdc0vfs8uqd1"
        ]
      }
    },
    {
      "id": "recRtTd8Cengk4Hkj",
      "createdTime": "2023-03-29T11:26:34.000Z",
      "fields": {
        "serializer": "M1M$",
        "function_name": [
          "recHYvq7XJQwDh8kf"
        ]
      }
    },
    {
      "id": "recS2HS7pCvseiOYA",
      "createdTime": "2023-10-27T07:06:24.000Z",
      "fields": {
        "serializer": "Rx",
        "function_name": [
          "recHrye06ZhjaJl4s"
        ]
      }
    },
    {
      "id": "recSFEaNSis7wCU03",
      "createdTime": "2023-03-29T11:29:41.000Z",
      "fields": {
        "serializer": "G$",
        "function_name": [
          "recdFCKk7OyqokYi0"
        ]
      }
    },
    {
      "id": "recWBkz5m50KnMKPw",
      "createdTime": "2024-01-25T16:36:23.000Z",
      "fields": {
        "serializer": "0b0100100010{$$$$$$$$}0001",
        "function_name": [
          "rec8QlWGjRukH7h7j"
        ]
      }
    },
    {
      "id": "recYyoDW8T7JtuQ8r",
      "createdTime": "2024-01-25T16:35:14.000Z",
      "fields": {
        "serializer": "0x0231415201",
        "function_name": [
          "recja3UnGaPLMJAoo"
        ]
      }
    },
    {
      "id": "reccQjb3Gl4Zrgx9s",
      "createdTime": "2023-03-29T11:26:34.000Z",
      "fields": {
        "serializer": "L1P0R$G$B$",
        "function_name": [
          "rec4QYxGhgVUbZ5qX"
        ]
      }
    },
    {
      "id": "recdb5aFXJ9f0s9gP",
      "createdTime": "2023-03-30T08:35:41.000Z",
      "fields": {
        "serializer": "C0P0",
        "function_name": [
          "recK2MzedyicCYDIC"
        ]
      }
    },
    {
      "id": "recdfllybYUfgvWVB",
      "createdTime": "2023-03-29T11:26:34.000Z",
      "fields": {
        "serializer": "A2M$S$",
        "function_name": [
          "recJzsnocyO4cIDOe"
        ]
      }
    },
    {
      "id": "recdpDOVn3LRSf3Oj",
      "createdTime": "2023-03-29T11:25:28.000Z",
      "fields": {
        "serializer": "A2X$Y$Z$",
        "function_name": [
          "rec5FD7F7MmyUrjkj"
        ]
      }
    },
    {
      "id": "recdtDaJNGgm5tJSm",
      "createdTime": "2023-03-29T11:26:34.000Z",
      "fields": {
        "serializer": "L$P$R$G$B$",
        "function_name": [
          "recocqYE6qupBf9Qo"
        ]
      }
    },
    {
      "id": "recf5joo9ofDkxO9v",
      "createdTime": "2023-03-29T11:25:28.000Z",
      "fields": {
        "serializer": "A1H",
        "function_name": [
          "recz1srMNzHdJKhZZ"
        ]
      }
    },
    {
      "id": "recfgZUUSJMCOrYDG",
      "createdTime": "2023-06-14T01:55:15.000Z",
      "fields": {
        "serializer": "M0",
        "function_name": [
          "recAjfR2l4fC9GWeI"
        ]
      }
    },
    {
      "id": "recligUMogrp3PlrL",
      "createdTime": "2023-10-27T07:06:15.000Z",
      "fields": {
        "serializer": "R$",
        "function_name": [
          "rec2yzkWSPvvme952"
        ]
      }
    },
    {
      "id": "recomhP3XL7GxMQXM",
      "createdTime": "2023-03-29T11:26:34.000Z",
      "fields": {
        "serializer": "P2E",
        "function_name": [
          "recm9D2w6RsHOT5hX"
        ]
      }
    },
    {
      "id": "recqFc8RGzq5baz41",
      "createdTime": "2023-09-27T00:07:03.000Z",
      "fields": {
        "serializer": "R0",
        "function_name": [
          "reczCM3odpotH9T60"
        ]
      }
    },
    {
      "id": "rectFfZu6iLfEZnzd",
      "createdTime": "2023-08-28T07:13:25.000Z",
      "fields": {
        "serializer": "R$T$",
        "function_name": [
          "recZIjbKNiXnSaMDF"
        ]
      }
    },
    {
      "id": "rectLeMvO9ETFHtFd",
      "createdTime": "2023-03-29T11:26:34.000Z",
      "fields": {
        "serializer": "T1S$",
        "function_name": [
          "rec6EEEjwAT5bGnuZ"
        ]
      }
    },
    {
      "id": "recwCqFQkr1SRAXqV",
      "createdTime": "2023-03-29T11:26:34.000Z",
      "fields": {
        "serializer": "A2X$Y$Z$R$",
        "function_name": [
          "recCbAGcQLgTNgiIq"
        ]
      }
    }
  ]
}